monitoring_scripts/__init__.py
monitoring_scripts/telegram_notification_host.py
monitoring_scripts/telegram_notification_service.py
monitoring_scripts-1.0.0.data/data/monitoring_scripts_doc/CHANGELOG.md
monitoring_scripts-1.0.0.data/data/monitoring_scripts_doc/LICENSE
monitoring_scripts-1.0.0.data/data/monitoring_scripts_doc/README.md
monitoring_scripts-1.0.0.dist-info/LICENSE
monitoring_scripts-1.0.0.dist-info/METADATA
monitoring_scripts-1.0.0.dist-info/WHEEL
monitoring_scripts-1.0.0.dist-info/top_level.txt
monitoring_scripts-1.0.0.dist-info/RECORD
