Metadata-Version: 2.1
Name: monitoring-scripts
Version: 1.0.0
Summary: Scripts for monitoring
Home-page: https://github.com/f-froehlich/monitoring-scripts
Author: Fabian Fröhlich
Author-email: mail@confgen.org
License: AGPLv3
Download-URL: https://pypi.org/project/monitoring-scripts/
Keywords: icinga,icinga2,icinga2-plugin,monitoring,nagios,nagios-plugin,nrpe,healthcheck,serverstatus
Platform: UNKNOWN
Requires-Dist: monitoring-utils (~=2.0.0)
